exemplify/__init__.py
exemplify/cli.py
exemplify/main.py
exemplify/steps/base.py
exemplify/steps/command.py
exemplify/steps/distro.py
exemplify/steps/link.py
exemplify/steps/node.py
exemplify/steps/python.py
exemplify/steps/rust.py
exemplify/steps/vcs.py
exemplify/util/merge.py
exemplify/util/python_path.py
exemplify-0.5.0.dist-info/METADATA
exemplify-0.5.0.dist-info/WHEEL
exemplify-0.5.0.dist-info/entry_points.txt
exemplify-0.5.0.dist-info/RECORD
